README.md
setup.py
SquashMatrixAPI/__init__.py
SquashMatrixAPI/api_client.py
SquashMatrixAPI/configuration.py
SquashMatrixAPI/rest.py
SquashMatrixAPI/SquashMatrixClientAPI/__init__.py
SquashMatrixAPI/SquashMatrixClientAPI/default_api.py
SquashMatrixAPI/SquashMatrixClientModel/__init__.py
SquashMatrixAPI/SquashMatrixClientModel/api_response_errors.py
SquashMatrixAPI/SquashMatrixClientModel/api_response_errors_errors.py
SquashMatrixAPI/SquashMatrixClientModel/club.py
SquashMatrixAPI/SquashMatrixClientModel/game.py
SquashMatrixAPI/SquashMatrixClientModel/inline_response_200.py
SquashMatrixAPI/SquashMatrixClientModel/inline_response_200_1.py
SquashMatrixAPI/SquashMatrixClientModel/inline_response_200_2.py
SquashMatrixAPI/SquashMatrixClientModel/inline_response_200_3.py
SquashMatrixAPI/SquashMatrixClientModel/inline_response_200_4.py
SquashMatrixAPI/SquashMatrixClientModel/inline_response_200_5.py
SquashMatrixAPI/SquashMatrixClientModel/player.py
squash_matrix_api.egg-info/PKG-INFO
squash_matrix_api.egg-info/SOURCES.txt
squash_matrix_api.egg-info/dependency_links.txt
squash_matrix_api.egg-info/requires.txt
squash_matrix_api.egg-info/top_level.txt
test/__init__.py
test/test_api_response_errors.py
test/test_api_response_errors_errors.py
test/test_club.py
test/test_default_api.py
test/test_game.py
test/test_inline_response_200.py
test/test_inline_response_200_1.py
test/test_inline_response_200_2.py
test/test_inline_response_200_3.py
test/test_inline_response_200_4.py
test/test_inline_response_200_5.py
test/test_player.py