Metadata-Version: 1.0
Name: squash-matrix-api
Version: 1.0.0
Summary: Squash Matrix API
Home-page: https://github.com/wilkosz/squash_matrix_io_sdks/tree/master/python
Author: joshuawilkosz
Author-email: joshuawilkosz@squashmatrix.io
License: UNKNOWN
Keywords: Swagger,Squash Matrix API
Platform: UNKNOWN
